miracleplus_tools/__init__.py
miracleplus_tools/selenium_loader/html_loader.py
miracleplus_tools/selenium_loader/lib/document.py
miracleplus_tools/selenium_loader/lib/selenium_driver.py
miracleplus_tools/translator/gpt_translator.py
miracleplus_tools/translator/translator.py
miracleplus_tools-0.0.6.dist-info/METADATA
miracleplus_tools-0.0.6.dist-info/WHEEL
miracleplus_tools-0.0.6.dist-info/RECORD
